SciServerApi/Authentication.py
SciServerApi/Files.py
SciServerApi/Jobs.py
SciServerApi/Opt.py
SciServerApi/__init__.py
SciServerApi-3.0.0.dist-info/LICENSE.txt
SciServerApi-3.0.0.dist-info/METADATA
SciServerApi-3.0.0.dist-info/WHEEL
SciServerApi-3.0.0.dist-info/top_level.txt
SciServerApi-3.0.0.dist-info/RECORD
